{"image":"https://ipfs.io/ipfs/Qmd9g6SwQaJ9az2phRejaG6v3EvYdVrjLqbi9a6UdAxiyt/1090.png","planet":"Kryo","tribe":"Aarani","characters":"Aarani - Grey Long Hair","clothes":"Dark Thong Bag","head":"Standard","back":"Standard","tattoos":"Standard","jewelry":"Standard","hair":"Standard","mouth":"Standard","up clothes":"Standard","faces":"Standard","legendary":"Standard","image_url":"https://ipfs.io/ipfs/Qmd9g6SwQaJ9az2phRejaG6v3EvYdVrjLqbi9a6UdAxiyt/1090.png","name":"Oxya #1090","description":"Oxya #1090"}