{"image":"https://ipfs.io/ipfs/QmYE84xPMkMZBvN3zWiZWqvvYmSPeKw2EcJEYavXS5xJgy/2639.png","planet":"Naya","tribe":"Sakaris","characters":"Sakaris - White Eyes","clothes":"Gold Rock Stones Snake","jewelry":"Brown Crown Sun","hair":"Black Glued Braid","head":"Standard","back":"Standard","tattoos":"Standard","mouth":"Standard","up clothes":"Standard","faces":"Standard","legendary":"Standard","image_url":"https://ipfs.io/ipfs/QmYE84xPMkMZBvN3zWiZWqvvYmSPeKw2EcJEYavXS5xJgy/2639.png","name":"Oxya #2639","description":"Oxya #2639"}