{"image":"https://ipfs.io/ipfs/QmeCLXcxRMyPaDC8vWJWxyMsL3RCuhLyAVcb3fAoNYNZ5q/3517.png","planet":"Luxion","tribe":"Hybrizz","characters":"Hybrizz - Purple","clothes":"Dark Body Cables","up clothes":"Silver Plastron","head":"Standard","back":"Standard","tattoos":"Standard","jewelry":"Standard","hair":"Standard","mouth":"Standard","faces":"Standard","legendary":"Standard","image_url":"https://ipfs.io/ipfs/QmeCLXcxRMyPaDC8vWJWxyMsL3RCuhLyAVcb3fAoNYNZ5q/3517.png","name":"Oxya #3517","description":"Oxya #3517"}