{"image":"https://ipfs.io/ipfs/QmYE84xPMkMZBvN3zWiZWqvvYmSPeKw2EcJEYavXS5xJgy/3576.png","planet":"Naya","tribe":"Sakaris","characters":"Sakaris - Green Eyes","back":"Silver Katana","clothes":"Black Feather Shoulders","tattoos":"Gold Mecanic","hair":"Brown Glued Braid","head":"Standard","jewelry":"Standard","mouth":"Standard","up clothes":"Standard","faces":"Standard","legendary":"Standard","image_url":"https://ipfs.io/ipfs/QmYE84xPMkMZBvN3zWiZWqvvYmSPeKw2EcJEYavXS5xJgy/3576.png","name":"Oxya #3576","description":"Oxya #3576"}