{"image":"https://ipfs.io/ipfs/QmeCLXcxRMyPaDC8vWJWxyMsL3RCuhLyAVcb3fAoNYNZ5q/4127.png","planet":"Luxion","tribe":"Hybrizz","characters":"Hybrizz - Red","clothes":"Black And Green Cyborg Body","up clothes":"Silver Shoulder Armor","head":"Standard","back":"Standard","tattoos":"Standard","jewelry":"Standard","hair":"Standard","mouth":"Standard","faces":"Standard","legendary":"Standard","image_url":"https://ipfs.io/ipfs/QmeCLXcxRMyPaDC8vWJWxyMsL3RCuhLyAVcb3fAoNYNZ5q/4127.png","name":"Oxya #4127","description":"Oxya #4127"}