{"image":"https://ipfs.io/ipfs/QmYE84xPMkMZBvN3zWiZWqvvYmSPeKw2EcJEYavXS5xJgy/4376.png","planet":"Naya","tribe":"Suri","characters":"Suri - Blue Eyes","back":"Gold Bow","clothes":"Black Silver Rock Stones Snake","tattoos":"Gold Line","jewelry":"Natural Crown Sun","hair":"Brown Dreadlocks","head":"Standard","mouth":"Standard","up clothes":"Standard","faces":"Standard","legendary":"Standard","image_url":"https://ipfs.io/ipfs/QmYE84xPMkMZBvN3zWiZWqvvYmSPeKw2EcJEYavXS5xJgy/4376.png","name":"Oxya #4376","description":"Oxya #4376"}