{"image":"https://ipfs.io/ipfs/QmYE84xPMkMZBvN3zWiZWqvvYmSPeKw2EcJEYavXS5xJgy/4388.png","planet":"Naya","tribe":"Suri","characters":"Suri - Verron Eyes","clothes":"Grey Feather Shoulders","tattoos":"Gold Mecanic","jewelry":"Orange Light Handsfree","hair":"Grey Big Messy Bun","head":"Standard","back":"Standard","mouth":"Standard","up clothes":"Standard","faces":"Standard","legendary":"Standard","image_url":"https://ipfs.io/ipfs/QmYE84xPMkMZBvN3zWiZWqvvYmSPeKw2EcJEYavXS5xJgy/4388.png","name":"Oxya #4388","description":"Oxya #4388"}