{"image":"https://ipfs.io/ipfs/Qmd9g6SwQaJ9az2phRejaG6v3EvYdVrjLqbi9a6UdAxiyt/4838.png","planet":"Kryo","tribe":"Kylma","characters":"Kylma - Black Beard And Hair","back":"Dark Bag","clothes":"Snow Heating Coat","head":"Standard","tattoos":"Standard","jewelry":"Standard","hair":"Standard","mouth":"Standard","up clothes":"Standard","faces":"Standard","legendary":"Standard","image_url":"https://ipfs.io/ipfs/Qmd9g6SwQaJ9az2phRejaG6v3EvYdVrjLqbi9a6UdAxiyt/4838.png","name":"Oxya #4838","description":"Oxya #4838"}