{"image":"https://ipfs.io/ipfs/Qmd9g6SwQaJ9az2phRejaG6v3EvYdVrjLqbi9a6UdAxiyt/5424.png","planet":"Kryo","tribe":"Vaalbara","characters":"Vaalbara - Shaved Head Brown Eyes","clothes":"Ice Heating Coat","head":"Black Knight Helmet","back":"Standard","tattoos":"Standard","jewelry":"Standard","hair":"Standard","mouth":"Standard","up clothes":"Standard","faces":"Standard","legendary":"Standard","image_url":"https://ipfs.io/ipfs/Qmd9g6SwQaJ9az2phRejaG6v3EvYdVrjLqbi9a6UdAxiyt/5424.png","name":"Oxya #5424","description":"Oxya #5424"}